awtrix/__init__.py
awtrix/device.py
awtrix/display.py
awtrix/effects.py
awtrix/icons.py
awtrix/palettes.py
awtrix/start.py
gkj_awtrix-0.1.0.dist-info/METADATA
gkj_awtrix-0.1.0.dist-info/WHEEL
gkj_awtrix-0.1.0.dist-info/entry_points.txt
gkj_awtrix-0.1.0.dist-info/RECORD
